setup.py
mymoduel_fuyd.egg-info/PKG-INFO
mymoduel_fuyd.egg-info/SOURCES.txt
mymoduel_fuyd.egg-info/dependency_links.txt
mymoduel_fuyd.egg-info/top_level.txt
src/__init__.py
src/test.py