Metadata-Version: 1.1
Name: mymoduel-fuyd
Version: 1.0.0
Summary: a distributed test framework
Home-page: http://www.osforce.cn
Author: fuyadong
Author-email: fuyadong2011@163.com
License: MIT
Keywords: framework nose testing
Platform: any
Classifier: Programming Language :: Python
